setup.py
django_jigsawview.egg-info/PKG-INFO
django_jigsawview.egg-info/SOURCES.txt
django_jigsawview.egg-info/dependency_links.txt
django_jigsawview.egg-info/not-zip-safe
django_jigsawview.egg-info/requires.txt
django_jigsawview.egg-info/top_level.txt
jigsawview/__init__.py
jigsawview/models.py
jigsawview/views.py
jigsawview/pieces/__init__.py
jigsawview/pieces/base.py
jigsawview/pieces/filter_search.py
jigsawview/pieces/form.py
jigsawview/pieces/formset.py
jigsawview/pieces/object.py
jigsawview/tests/__init__.py
jigsawview/tests/models.py
jigsawview/tests/urls.py
jigsawview/tests/views.py