Metadata-Version: 1.0
Name: django-jigsawview
Version: 0.1.0
Summary: An extended alternative to Django generic class based views.
Home-page: https://github.com/linovia/django-jigsawview
Author: Xavier Ordoquy
Author-email: xordoquy@linovia.com
License: BSD
Platform: UNKNOWN
Classifier: Framework :: Django
Classifier: Operating System :: OS Independent
Classifier: Intended Audience :: Developers
Classifier: Programming Language :: Python
Classifier: Environment :: Web Environment
Classifier: Development Status :: 2 - Pre-Alpha
Classifier: Programming Language :: Python :: 3
Classifier: Programming Language :: Python
